bigga/__init__.py
bigga/bigga.py
bigga/cli.py
bigga/config.py
bigga/main.py
bigga/tasks.py
bigga/contrib/__init__.py
bigga/contrib/fabtools/__init__.py
bigga/contrib/fabtools/user.py
bigga/contrib/fabtools/require/__init__.py
bigga/contrib/patchwork/__init__.py
bigga/contrib/patchwork/info.py
bigga/contrib/patchwork/packages/__init__.py
bigga-0.2.1.dist-info/LICENSE
bigga-0.2.1.dist-info/METADATA
bigga-0.2.1.dist-info/WHEEL
bigga-0.2.1.dist-info/entry_points.txt
bigga-0.2.1.dist-info/top_level.txt
bigga-0.2.1.dist-info/RECORD
