Metadata-Version: 2.1
Name: bigga
Version: 0.2.1
Summary: A simple CLI tool to deploy Python & Node microservices on linux instaces. Built on top of invoke, fabric and patchwork.
Home-page: https://github.com/reckonsys/bigga
Author: dhilipsiva
Author-email: dhilipsiva@pm.me
License: MIT
Keywords: bigga reckonsys cli deploy deployment
Platform: UNKNOWN
Classifier: Development Status :: 4 - Beta
Classifier: Intended Audience :: Developers
Classifier: License :: OSI Approved :: MIT License
Classifier: Programming Language :: Python :: 3
Classifier: Programming Language :: Python :: 3.7
Requires-Dist: invoke
Requires-Dist: fabric
Requires-Dist: patchwork
